fraudmetrics/__init__.py
fraudmetrics/plot_curves.py
fraudmetrics/rank_based.py
fraudmetrics/threshold_free.py
fraudmetrics/thresholded.py
fraudmetrics/value_based.py
fraudmetrics/utils/__init__.py
fraudmetrics/utils/validate_inputs.py
fraudmetrics-0.3.1.dist-info/METADATA
fraudmetrics-0.3.1.dist-info/WHEEL
fraudmetrics-0.3.1.dist-info/licenses/LICENSE
fraudmetrics-0.3.1.dist-info/RECORD
