Metadata-Version: 2.4
Name: fraudmetrics
Version: 0.3.1
Summary: A comprehensive Python library for evaluating fraud detection models with specialized metrics for business impact analysis
Project-URL: Homepage, https://github.com/yashasnadigsyn/fraudmetrics
Project-URL: Repository, https://github.com/yashasnadigsyn/fraudmetrics
Project-URL: Documentation, https://github.com/yashasnadigsyn/fraudmetrics#readme
Project-URL: Issues, https://github.com/yashasnadigsyn/fraudmetrics/issues
Author-email: Yashas Nadig <yashasnadigsyn@outlook.com>
License: MIT
License-File: LICENSE
Keywords: binary-classification,evaluation,fraud-detection,machine-learning,metrics
Classifier: Development Status :: 4 - Beta
Classifier: Intended Audience :: Developers
Classifier: Intended Audience :: Science/Research
Classifier: License :: OSI Approved :: MIT License
Classifier: Operating System :: OS Independent
Classifier: Programming Language :: Python :: 3
Classifier: Programming Language :: Python :: 3.11
Classifier: Programming Language :: Python :: 3.12
Classifier: Topic :: Scientific/Engineering :: Artificial Intelligence
Classifier: Topic :: Software Development :: Libraries :: Python Modules
Requires-Python: >=3.11
Requires-Dist: matplotlib>=3.10.0
Requires-Dist: numpy>2.0
Requires-Dist: pandas>2.2
Requires-Dist: seaborn>=0.13.2
Provides-Extra: dev
Requires-Dist: black>=23.0.0; extra == 'dev'
Requires-Dist: flake8>=6.0.0; extra == 'dev'
Requires-Dist: pytest-cov>=4.0.0; extra == 'dev'
Requires-Dist: pytest>=7.0.0; extra == 'dev'
